AcodisApiHandler/__init__.py
AcodisApiHandler/_acodis_auth.py
AcodisApiHandler/_acodis_logger.py
AcodisApiHandler/_version.py
AcodisApiHandler/acodis_error.py
AcodisApiHandler/acodis_handler.py
AcodisApiHandler/acodis_parser.py
AcodisApiHandler-0.3.7.dist-info/LICENSE
AcodisApiHandler-0.3.7.dist-info/METADATA
AcodisApiHandler-0.3.7.dist-info/WHEEL
AcodisApiHandler-0.3.7.dist-info/top_level.txt
AcodisApiHandler-0.3.7.dist-info/RECORD
