Metadata-Version: 2.1
Name: AcodisApiHandler
Version: 0.3.7
Summary: A simple API handler for Python
Author-email: "Ricardo F. dos Santos" <ricardofilipecdsantos@gmail.com>
License: MIT License
Keywords: api,handler,python,acodis
Classifier: Development Status :: 4 - Beta
Classifier: Intended Audience :: Developers
Classifier: License :: OSI Approved :: MIT License
Classifier: Operating System :: OS Independent
Classifier: Programming Language :: Python :: 3
Classifier: Programming Language :: Python :: 3.8
Classifier: Programming Language :: Python :: 3.9
Classifier: Programming Language :: Python :: 3.10
Classifier: Topic :: Software Development :: Libraries :: Python Modules
Requires-Python: >=3.8.12
License-File: LICENSE
Requires-Dist: pandas ==1.5.2
Requires-Dist: requests ==2.28.1
